LICENSE
MANIFEST.in
README.md
setup.py
NextBFootBallAnalysis/__init__.py
NextBFootBallAnalysis.egg-info/PKG-INFO
NextBFootBallAnalysis.egg-info/SOURCES.txt
NextBFootBallAnalysis.egg-info/dependency_links.txt
NextBFootBallAnalysis.egg-info/entry_points.txt
NextBFootBallAnalysis.egg-info/requires.txt
NextBFootBallAnalysis.egg-info/top_level.txt
NextBFootBallAnalysis/cli/__init__.py
NextBFootBallAnalysis/cli/cli_get_last_matchs.py
NextBFootBallAnalysis/cli/cli_get_markdown.py
NextBFootBallAnalysis/cli/cli_get_match.py
NextBFootBallAnalysis/cli/cli_get_recommend.py
NextBFootBallAnalysis/cli/cli_get_team.py
NextBFootBallAnalysis/cli/cli_init_football_db.py
NextBFootBallAnalysis/cli/cli_simulation.py
NextBFootBallAnalysis/libs/NextBFootball.db
NextBFootBallAnalysis/libs/__init__.py
NextBFootBallAnalysis/libs/common.py
NextBFootBallAnalysis/libs/constant.py
NextBFootBallAnalysis/libs/sqlite_db.py
NextBFootBallAnalysis/libs/strategy/__init__.py
NextBFootBallAnalysis/libs/strategy/strategy_common.py
NextBFootBallAnalysis/libs/strategy/strategy_one.py
NextBFootBallAnalysis/libs/strategy/strategy_three.py
NextBFootBallAnalysis/libs/strategy/strategy_two.py