Metadata-Version: 2.1
Name: NextBFootBallAnalysis
Version: 2.1.10
Summary: NextB的足球比赛数据分析
Home-page: https://github.com/a232319779/NextBFootBallAnalysis
Author: ddvv
Author-email: dadavivi512@gmail.com
License: MIT
Platform: UNKNOWN
Classifier: Programming Language :: Python :: 3
Classifier: License :: OSI Approved :: MIT License
Classifier: Operating System :: OS Independent
Requires-Python: >=3.6
License-File: LICENSE
